electionsBR/__init__.py
electionsBR/api.py
electionsBR/columns.py
electionsBR/backend/__init__.py
electionsBR/backend/client.py
electionsBR-0.0.5.dist-info/METADATA
electionsBR-0.0.5.dist-info/WHEEL
electionsBR-0.0.5.dist-info/top_level.txt
electionsBR-0.0.5.dist-info/RECORD
