Metadata-Version: 2.1
Name: electionsBR
Version: 0.0.5
Summary: A python wrapper to fetch votes from BR elections
Home-page: https://github.com/Cepesp-Fgv/cepesp-python
Author: Abraao Barros
Author-email: abraaobarros3@gmail.com
License: UNKNOWN
Platform: UNKNOWN
Classifier: Programming Language :: Python :: 3
Classifier: License :: OSI Approved :: MIT License
Classifier: Operating System :: OS Independent
Requires-Dist: pandas
Requires-Dist: requests
